bails_lambda_utils/__init__.py
bails_lambda_utils/encoders.py
bails_lambda_utils/errors.py
bails_lambda_utils/handler.py
bails_lambda_utils/misc.py
bails_lambda_utils/responses.py
test/__init__.py
test/encoders_test.py
test/handler_test.py
test/misc_test.py
test/response_test.py
bails_lambda_utils-0.3.0.dist-info/METADATA
bails_lambda_utils-0.3.0.dist-info/WHEEL
bails_lambda_utils-0.3.0.dist-info/top_level.txt
bails_lambda_utils-0.3.0.dist-info/RECORD
