Metadata-Version: 2.1
Name: bails-lambda-utils
Version: 0.3.0
Summary: For making lambdas easier
Home-page: https://github.com/beverts312/lambda-utils
Author: Bailey Everts
Author-email: me@baileyeverts.net
License: MIT
Platform: UNKNOWN
Requires-Dist: pynamodb
